django_nextjs/__init__.py
django_nextjs/app_settings.py
django_nextjs/apps.py
django_nextjs/asgi.py
django_nextjs/exceptions.py
django_nextjs/proxy.py
django_nextjs/render.py
django_nextjs/urls.py
django_nextjs/utils.py
django_nextjs/views.py
django_nextjs/templates/django_nextjs/document_base.html
django_nextjs-3.3.0.dist-info/licenses/LICENSE
django_nextjs-3.3.0.dist-info/METADATA
django_nextjs-3.3.0.dist-info/WHEEL
django_nextjs-3.3.0.dist-info/top_level.txt
django_nextjs-3.3.0.dist-info/RECORD
